HDGTest/test1.py
HDGTest/test2.py
HDGTest-0.0.0.3.dist-info/METADATA
HDGTest-0.0.0.3.dist-info/WHEEL
HDGTest-0.0.0.3.dist-info/top_level.txt
HDGTest-0.0.0.3.dist-info/RECORD
