Metadata-Version: 2.1
Name: HDGTest
Version: 0.0.0.3
Summary: My First Test Package
Home-page: UNKNOWN
Author: Dong gook Hong 
Author-email: dgh5ng@naver.com
License: MIT
Platform: UNKNOWN
Requires-Python: >3
